rxv/.gitignore
rxv/__init__.py
rxv/exceptions.py
rxv/rxv.py
rxv/ssdp.py
rxv/version.py
rxv-0.7.0.dist-info/LICENSE
rxv-0.7.0.dist-info/METADATA
rxv-0.7.0.dist-info/WHEEL
rxv-0.7.0.dist-info/top_level.txt
rxv-0.7.0.dist-info/RECORD
